htmlight/__init__.py
htmlight-0.2.0.dist-info/METADATA
htmlight-0.2.0.dist-info/WHEEL
htmlight-0.2.0.dist-info/licenses/LICENSE
htmlight-0.2.0.dist-info/RECORD
