Metadata-Version: 2.4
Name: htmlight
Version: 0.2.0
Summary: Light html generator
License: GNU General Public License v3.0
License-File: LICENSE
Keywords: html
Author: Kostiantyn Shmyhelskyi
Author-email: graflearnt@gmail.com
Requires-Python: >=3.9,<4.0
Classifier: License :: Other/Proprietary License
Classifier: Programming Language :: Python :: 3
Classifier: Programming Language :: Python :: 3.9
Classifier: Programming Language :: Python :: 3.10
Classifier: Programming Language :: Python :: 3.11
Classifier: Programming Language :: Python :: 3.12
Classifier: Programming Language :: Python :: 3.13
Classifier: Programming Language :: Python :: 3.14
Project-URL: Documentation, https://github.com/GrafLearnt/htmlight/blob/main/README.md
Project-URL: Homepage, https://github.com/GrafLearnt/htmlight
